rdfsx-0.1.0.dist-info/METADATA
rdfsx-0.1.0.dist-info/WHEEL
rdfsx.libs/libgcc_s-e52197c3.so.1
rdfsx/__init__.py
rdfsx/rdfsx.abi3.so
rdfsx-0.1.0.dist-info/RECORD
