Metadata-Version: 2.3
Name: rdfsx
Version: 0.1.0
Summary: RDF data shapes implementation in Rust
Keywords: rdf,linked-data,semantic-web,shex
Home-Page: https://www.weso.es/shapes-rs/
Author: Jose Emilio Labra Gayo <labra@uniovi.es>, Ángel Iglesias Préstamo <angel.iglesias.prestamo@gmail.com>, Marc-Antoine Arnaud <marc-antoine.arnaud@luminvent.com>
Author-email: Jose Emilio Labra Gayo <labra@uniovi.es>, Ángel Iglesias Préstamo <angel.iglesias.prestamo@gmail.com>, Marc-Antoine Arnaud <marc-antoine.arnaud@luminvent.com>
License: MIT OR Apache-2.0
Project-URL: Source Code, https://github.com/weso/shapes-rs
